{
    "packageName": "connect20\/Dextrous_Extendcatalog",
    "packageVersion": "1.2.0",
    "signature": "-----BEGIN PGP SIGNATURE-----\nVersion: GnuPG v1\n\niF4EABEIAAYFAlaTEMQACgkQZi3Wes40mG6JuAD+JUqxt15v0PUlN\/vtgJ3fWHxt\n30mCacao5UqROao43pwA\/3\/iJ2IWIlChxDH0nlIuixAx8\/+uwLag++gfVhvlo\/+V\n=3xbL\n-----END PGP SIGNATURE-----\n",
    "signatureType": "gpg",
    "downloadUrl": "http:\/\/connect20.magentocommerce.com\/community\/Dextrous_Extendcatalog\/1.2.0\/Dextrous_Extendcatalog-1.2.0.tgz",
    "sha256": "031b43e3c7ce8bdb8865f525885442783331d48a12ef6be5f114c1124493656b"
}