{
    "packageName": "connect20\/Daffodil_Stock",
    "packageVersion": "1.0.0.3",
    "signature": "-----BEGIN PGP SIGNATURE-----\nVersion: GnuPG v1\n\niF4EABEIAAYFAlaTEBAACgkQZi3Wes40mG4A5wEAjltJmw3X3m5wd8\/\/0xmI1dTq\nPoo7j6yCT07Wag2YDIcA\/AzvDs\/dNww7KztZj6qSMhzoOS67ywp8kX\/uYXrcUubr\n=TpUr\n-----END PGP SIGNATURE-----\n",
    "signatureType": "gpg",
    "downloadUrl": "http:\/\/connect20.magentocommerce.com\/community\/Daffodil_Stock\/1.0.0.3\/Daffodil_Stock-1.0.0.3.tgz",
    "sha256": "b223bfad709ad7788aee67e29d06b5f7d0f93641d2ff5de83129781f23b66183"
}