{
    "packageName": "connect20\/Fontis_CampaignMonitor",
    "packageVersion": "0.5.2",
    "signature": "-----BEGIN PGP SIGNATURE-----\nVersion: GnuPG v1\n\niF4EABEIAAYFAlaTcb4ACgkQZi3Wes40mG7WCAEAsgxgwQNvb8s5IOjcROZ2Dm9q\n2RlxxefNiGVFLN97Pi4A\/22GLNh2brJfFwDqaWmoiun3bWrAegSsrKmHctOJWEuO\n=zw4m\n-----END PGP SIGNATURE-----\n",
    "signatureType": "gpg",
    "downloadUrl": "http:\/\/connect20.magentocommerce.com\/community\/Fontis_CampaignMonitor\/0.5.2\/Fontis_CampaignMonitor-0.5.2.tgz",
    "sha256": "c0953cfad293da770c15f9249e0d389131c1fbf1575dfb09a1aefdf1480e7aaf"
}