{
    "packageName": "connect20\/Owebia_Shipping_2",
    "packageVersion": "2.1.1",
    "signature": "-----BEGIN PGP SIGNATURE-----\nVersion: GnuPG v1\n\niF4EABEIAAYFAlaUDz4ACgkQZi3Wes40mG5ODAD+JTln79PtecAmF3BnO\/DAdwKT\nz37X7B9fTfOe18XtsU0BAKhnPt\/om\/RPr\/51d4QiD1rpbxkRbyuGXbre75Q+35GY\n=VOkS\n-----END PGP SIGNATURE-----\n",
    "signatureType": "gpg",
    "downloadUrl": "http:\/\/connect20.magentocommerce.com\/community\/Owebia_Shipping_2\/2.1.1\/Owebia_Shipping_2-2.1.1.tgz",
    "sha256": "3241c077891f98ab6c48bb6327c5805401b940fb1ba5eef4cd80787585c28473"
}