{
    "packageName": "connect20\/Ced_LayBuy",
    "packageVersion": "2.0.7",
    "signature": "-----BEGIN PGP SIGNATURE-----\nVersion: GnuPG v1\n\niF4EABEIAAYFAlaTClkACgkQZi3Wes40mG5+agD+KkiLdJpTM\/ZxdssKSMcvQryc\n8xd3+F+PavR14YoladoA+QFv6bCKe1\/86f9y+mIlH4NbUjkZi3b6m\/ZA25wEDNAs\n=PmfL\n-----END PGP SIGNATURE-----\n",
    "signatureType": "gpg",
    "downloadUrl": "http:\/\/connect20.magentocommerce.com\/community\/Ced_LayBuy\/2.0.7\/Ced_LayBuy-2.0.7.tgz",
    "sha256": "0fc328e9ed48c6b52544ca559cf6568b773810e0bbbe3d1bf1582d1d31a78476"
}