{
    "packageName": "connect20\/Around_io",
    "packageVersion": "1.2.4",
    "signature": "-----BEGIN PGP SIGNATURE-----\nVersion: GnuPG v1\n\niF4EABEIAAYFAlaTA7kACgkQZi3Wes40mG7fYwD9EVrUysBiQrr7jCl5iROjQqDX\nTF3rA7S407YGreuCk9EA\/28zXYAEAzUqx5G2F2SevBDrIl\/XCWv\/5yqRDSbEs+9I\n=LmUo\n-----END PGP SIGNATURE-----\n",
    "signatureType": "gpg",
    "downloadUrl": "http:\/\/connect20.magentocommerce.com\/community\/Around_io\/1.2.4\/Around_io-1.2.4.tgz",
    "sha256": "77a4435fbbe1acc65d7188f0adfab1b89b409fb8407c98114ce61db9310ab1a4"
}