{
    "packageName": "connect20\/bb_bnr",
    "packageVersion": "1.0.0",
    "signature": "-----BEGIN PGP SIGNATURE-----\nVersion: GnuPG v1\n\niF4EABEIAAYFAlaTBmsACgkQZi3Wes40mG6kAQD\/b+nhT7+p1gwNosJaPEPyQBsk\n5MhyMlPIaDQ6A3lzlCUA\/RlyNJVNlYmwL5Si2QMTJ+4w6DhknnEko467LPcUe6ZZ\n=QxjV\n-----END PGP SIGNATURE-----\n",
    "signatureType": "gpg",
    "downloadUrl": "http:\/\/connect20.magentocommerce.com\/community\/bb_bnr\/1.0.0\/bb_bnr-1.0.0.tgz",
    "sha256": "ccc195323b1973c6a8f91dc8be62f6b47beead1beae79e3be151525d3e9709a0"
}