{
    "packageName": "connect20\/TroopID_Connect",
    "packageVersion": "0.2.0",
    "signature": "-----BEGIN PGP SIGNATURE-----\nVersion: GnuPG v1\n\niF4EABEIAAYFAlaUIwcACgkQZi3Wes40mG7yuwD8DAaSb7Nhy81hVASbJ8UH14MG\nFRMU0TuqoPvkmaaZpTYA\/A93id4TQofoAdFYubJTCvm\/2DPjt\/iYLtneeIrwcoE9\n=HlSS\n-----END PGP SIGNATURE-----\n",
    "signatureType": "gpg",
    "downloadUrl": "http:\/\/connect20.magentocommerce.com\/community\/TroopID_Connect\/0.2.0\/TroopID_Connect-0.2.0.tgz",
    "sha256": "b48bc75729c26cf05577ca34883818ba0dbc38cf79e99842500c69430c7c9024"
}