{
    "packageName": "connect20\/unbxd_recommendation",
    "packageVersion": "1.0.6",
    "signature": "-----BEGIN PGP SIGNATURE-----\nVersion: GnuPG v1\n\niF4EABEIAAYFAlaUJKwACgkQZi3Wes40mG5McwEAjWXros7VDRLgVh0vFtNT3C2a\niEVtvE2MCxF\/n2Mn\/ScA\/imxpuDI5jdvFaREyXXR+ZrIdDCDtmWPG2U11Rod\/pqR\n=whs4\n-----END PGP SIGNATURE-----\n",
    "signatureType": "gpg",
    "downloadUrl": "http:\/\/connect20.magentocommerce.com\/community\/unbxd_recommendation\/1.0.6\/unbxd_recommendation-1.0.6.tgz",
    "sha256": "d7ea3470d1a5bfb958a40c77b1dcd922bdfdf7565b8b5bc5dbd57bd0d4867ca7"
}