{
    "packageName": "connect20\/P3chat_Chat",
    "packageVersion": "0.1.1",
    "signature": "-----BEGIN PGP SIGNATURE-----\nVersion: GnuPG v1\n\niF4EABEIAAYFAlaUD1AACgkQZi3Wes40mG7AGAD7Bmzh7Qxpf\/vK1aGI+uS8ZTIN\nuOi7znc0oV2D\/PeWeVkA\/Ru2isNNd5cHnuIskrm7HnDyVEUAzhmcaLDY3DrbGqxj\n=2Fgs\n-----END PGP SIGNATURE-----\n",
    "signatureType": "gpg",
    "downloadUrl": "http:\/\/connect20.magentocommerce.com\/community\/P3chat_Chat\/0.1.1\/P3chat_Chat-0.1.1.tgz",
    "sha256": "352f09fb9c7127431b5900508fc64308c44a879b5a442ebfda0083638f58df9c"
}