{
    "packageName": "connect20\/yapital",
    "packageVersion": "1.1.0",
    "signature": "-----BEGIN PGP SIGNATURE-----\nVersion: GnuPG v1\n\niF4EABEIAAYFAlaUKAIACgkQZi3Wes40mG6mCgD+NjX2c0cizma7EcY0PHK0TVB5\nO1yStMT2avRvWlfZekUA\/jcU0j5OTT3gETlC\/FVsf5CR+pvfsE6TcaJ+P34ew5Sk\n=bpH9\n-----END PGP SIGNATURE-----\n",
    "signatureType": "gpg",
    "downloadUrl": "http:\/\/connect20.magentocommerce.com\/community\/yapital\/1.1.0\/yapital-1.1.0.tgz",
    "sha256": "b9818a43abbbf6828f0e6b2c52d527fce2f3e8e37116a2531c0e5d2938915c42"
}