{
    "packageName": "connect20\/Ewall_Customtags",
    "packageVersion": "1.0.1",
    "signature": "-----BEGIN PGP SIGNATURE-----\nVersion: GnuPG v1\n\niF4EABEIAAYFAlaTaLQACgkQZi3Wes40mG4\/YAEAkBD9ACsSYwtetQ\/+\/aglgTET\n6+Pn5He1reBz3hMaqb4A\/3D+kOjO3SaovABuh+Y0nssYC7UuaI173gK8B42cb+hi\n=QaBD\n-----END PGP SIGNATURE-----\n",
    "signatureType": "gpg",
    "downloadUrl": "http:\/\/connect20.magentocommerce.com\/community\/Ewall_Customtags\/1.0.1\/Ewall_Customtags-1.0.1.tgz",
    "sha256": "48ddc22449413891e78e567933f866aca22e09a8fadbb279fb64b9ca320f09fa"
}