{
    "packageName": "connect20\/Zenstores_Core",
    "packageVersion": "1.0.1",
    "signature": "-----BEGIN PGP SIGNATURE-----\nVersion: GnuPG v1\n\niF4EABEIAAYFAlaUKaYACgkQZi3Wes40mG6pXQEAsiYrzfKdTMFeT3GG2RiPksMt\n3F16X2zOHrCP\/9tvl54BAITUQrRsEHqy59TB173I20AQeT\/BWlnNc5riZPtD0Wfj\n=mGGk\n-----END PGP SIGNATURE-----\n",
    "signatureType": "gpg",
    "downloadUrl": "http:\/\/connect20.magentocommerce.com\/community\/Zenstores_Core\/1.0.1\/Zenstores_Core-1.0.1.tgz",
    "sha256": "ec5f5c479e6c9d5b6947ce97dcb0e1cc2a92da0c573b9d0e7eae27269a0460fc"
}