{
    "packageName": "connect20\/Sourav_QuantityDropdown",
    "packageVersion": "2.0.1",
    "signature": "-----BEGIN PGP SIGNATURE-----\nVersion: GnuPG v1\n\niF4EABEIAAYFAlaUHQsACgkQZi3Wes40mG7D5gD+JsCSAhCF\/x1p7RuMpGLL2LFd\nPY5MV31CxnwEabL91qoA\/jRdMZLcLKY9CM+kSOhzwDw8mmgZ5dYL1pbjJIi763io\n=le28\n-----END PGP SIGNATURE-----\n",
    "signatureType": "gpg",
    "downloadUrl": "http:\/\/connect20.magentocommerce.com\/community\/Sourav_QuantityDropdown\/2.0.1\/Sourav_QuantityDropdown-2.0.1.tgz",
    "sha256": "916269432fbde767a9dd5132f4b1e8087111b12e9e5145663620dde0f61d8e5a"
}