{
    "packageName": "connect20\/YOOCHOOSE_Recommender_Engine",
    "packageVersion": "1.2.2",
    "signature": "-----BEGIN PGP SIGNATURE-----\nVersion: GnuPG v1\n\niF4EABEIAAYFAlaUKRoACgkQZi3Wes40mG6a9gD8CZGVs3fwFeuitG0+euLRWzG4\nvdInuqw+q1PuKWOa00UA\/2+6u5DBa0rXtYhvv+Y\/MhwtYyTg7iA\/s+TA4PwN5Aq4\n=+Lv5\n-----END PGP SIGNATURE-----\n",
    "signatureType": "gpg",
    "downloadUrl": "http:\/\/connect20.magentocommerce.com\/community\/YOOCHOOSE_Recommender_Engine\/1.2.2\/YOOCHOOSE_Recommender_Engine-1.2.2.tgz",
    "sha256": "0da43e28c669ac8f799275a0294da132496a098c78967c3ea13ccc5ca3f297ca"
}