{
    "packageName": "connect20\/666999",
    "packageVersion": "0.5.1",
    "signature": "-----BEGIN PGP SIGNATURE-----\nVersion: GnuPG v1\n\niF4EABEIAAYFAlaS\/0gACgkQZi3Wes40mG4KyAD9Hse6A7m1BUh3vnxwxrt9YtKD\nWScFRCUMOoGEoIq2nnIA\/146AdZuLgiylqbRRAa1Xn4uYSbF0IirFEPN1Tsd55Dz\n=55Vk\n-----END PGP SIGNATURE-----\n",
    "signatureType": "gpg",
    "downloadUrl": "http:\/\/connect20.magentocommerce.com\/community\/666999\/0.5.1\/666999-0.5.1.tgz",
    "sha256": "c880f570e61bd6f194cd92a3a3ae386c630a6a43029f9195decd37e6de9f1147"
}