{
    "packageName": "connect20\/Responsivebannerslider",
    "packageVersion": "1.1.7",
    "signature": "-----BEGIN PGP SIGNATURE-----\nVersion: GnuPG v1\n\niF4EABEIAAYFAlaUFlwACgkQZi3Wes40mG4mkwEAnPxM7yJdMLxNrtHdk82ZtECJ\nHvCSdWPdoO2UMc8ukBcA\/3fCu5pa3j4PPpCpka+zEz8Lp7LfDiFcoaHvthgMv5vk\n=sSXS\n-----END PGP SIGNATURE-----\n",
    "signatureType": "gpg",
    "downloadUrl": "http:\/\/connect20.magentocommerce.com\/community\/Responsivebannerslider\/1.1.7\/Responsivebannerslider-1.1.7.tgz",
    "sha256": "50751f083b37baba104d4a2aad4871a101bac63d59d452b5bc5f3569026d6969"
}