{
    "packageName": "connect20\/Medma_News_Innovations",
    "packageVersion": "0.1.1",
    "signature": "-----BEGIN PGP SIGNATURE-----\nVersion: GnuPG v1\n\niF4EABEIAAYFAlaUBPAACgkQZi3Wes40mG4FfQD\/aAf72ng4kLdRHSluRyaeYVys\nkYcaarQ9ObslgM3z0BcA\/iWlFG9wDFVFbcV12AdwGVkTiZ\/wkOpw6I5cHzXSiTyT\n=palE\n-----END PGP SIGNATURE-----\n",
    "signatureType": "gpg",
    "downloadUrl": "http:\/\/connect20.magentocommerce.com\/community\/Medma_News_Innovations\/0.1.1\/Medma_News_Innovations-0.1.1.tgz",
    "sha256": "d567939b74dea1bfc8411b5c4517b6c0d85e090115a8dad696c56f36ed0f4235"
}