{
    "packageName": "connect20\/Swym_Relay",
    "packageVersion": "1.9.0",
    "signature": "-----BEGIN PGP SIGNATURE-----\nVersion: GnuPG v1\n\niF4EABEIAAYFAlaUH70ACgkQZi3Wes40mG4+cAD\/dVeEHV+Coz88tmCgX22Rydo4\nahDWaVJmhDBBTadE5mcBAKsf0gP5ln7VnWo026n4\/t+RyUJYR8xD33uuj8H155pC\n=RWWk\n-----END PGP SIGNATURE-----\n",
    "signatureType": "gpg",
    "downloadUrl": "http:\/\/connect20.magentocommerce.com\/community\/Swym_Relay\/1.9.0\/Swym_Relay-1.9.0.tgz",
    "sha256": "6b2796933f8eecbc466e4aa1072cc12a95d9f9f7c90337e6eb02ab6325ca285f"
}