{
    "packageName": "connect20\/Minubo_Interface",
    "packageVersion": "1.0.3",
    "signature": "-----BEGIN PGP SIGNATURE-----\nVersion: GnuPG v1\n\niF4EABEIAAYFAlaUBbYACgkQZi3Wes40mG7CuwD\/YvjcaWP\/nwy5UHjDgWgDulHA\nKUXPiUd+xVdO0nO5PAUA\/jgnCzTr0nyY52n0Jx78jQHLnGz6POypkqL5fm\/rPvw2\n=cPXp\n-----END PGP SIGNATURE-----\n",
    "signatureType": "gpg",
    "downloadUrl": "http:\/\/connect20.magentocommerce.com\/community\/Minubo_Interface\/1.0.3\/Minubo_Interface-1.0.3.tgz",
    "sha256": "8923ae2c3a751d063a08851fe931e27a6e211f90575d44a270c251031b83ec77"
}