{
    "packageName": "connect20\/flywebdesign_paypalfee",
    "packageVersion": "1.0.2",
    "signature": "-----BEGIN PGP SIGNATURE-----\nVersion: GnuPG v1\n\niF4EABEIAAYFAlaTcYsACgkQZi3Wes40mG7ZoQD\/RmdmPqklDp+3xsFQs2S50D8L\n6FZGfnmLdz5Zv0bUmRcBAJLFNJ4gfbXFEIhLOv1zHL2qH4yJwm1eeLVCaoeZMY82\n=5cDT\n-----END PGP SIGNATURE-----\n",
    "signatureType": "gpg",
    "downloadUrl": "http:\/\/connect20.magentocommerce.com\/community\/flywebdesign_paypalfee\/1.0.2\/flywebdesign_paypalfee-1.0.2.tgz",
    "sha256": "cbdd5d8786265c1270ff2da04cafd53b0c18b50fa5322bd16f0a5462d1e960a8"
}