{
    "packageName": "connect20\/Creativestyle_AmazonPayments",
    "packageVersion": "1.6.0",
    "signature": "-----BEGIN PGP SIGNATURE-----\nVersion: GnuPG v1\n\niF4EABEIAAYFAlaTD2wACgkQZi3Wes40mG5xrwEAsZOhUsRYMQFjWJzjQchV+esT\nCWdz9c5ANzOV4QJVUb8A\/1I5ewxDTOX97W3qM6IEnswe5veSGjCMhnMbQ2yoP8xF\n=VRVu\n-----END PGP SIGNATURE-----\n",
    "signatureType": "gpg",
    "downloadUrl": "http:\/\/connect20.magentocommerce.com\/community\/Creativestyle_AmazonPayments\/1.6.0\/Creativestyle_AmazonPayments-1.6.0.tgz",
    "sha256": "13017fc18d03b06a12e79447876bffc852b03bd3b35c622a0bb27eb7bd1570cd"
}